diagram_to_iac/__init__.py
diagram_to_iac/cli.py
diagram_to_iac/config.yaml
diagram_to_iac/r2d.py
diagram_to_iac/actions/__init__.py
diagram_to_iac/actions/git_entry.py
diagram_to_iac/actions/supervisor_entry.py
diagram_to_iac/actions/terraform_agent_entry.py
diagram_to_iac/agents/__init__.py
diagram_to_iac/agents/demonstrator_langgraph/__init__.py
diagram_to_iac/agents/demonstrator_langgraph/agent.py
diagram_to_iac/agents/demonstrator_langgraph/config.yaml
diagram_to_iac/agents/git_langgraph/__init__.py
diagram_to_iac/agents/git_langgraph/agent.py
diagram_to_iac/agents/git_langgraph/config.yaml
diagram_to_iac/agents/git_langgraph/pr.py
diagram_to_iac/agents/hello_langgraph/__init__.py
diagram_to_iac/agents/hello_langgraph/agent.py
diagram_to_iac/agents/hello_langgraph/config.yaml
diagram_to_iac/agents/policy_agent/__init__.py
diagram_to_iac/agents/policy_agent/agent.py
diagram_to_iac/agents/policy_agent/config.yaml
diagram_to_iac/agents/policy_agent/integration_example.py
diagram_to_iac/agents/policy_agent/tools/__init__.py
diagram_to_iac/agents/policy_agent/tools/tfsec_tool.py
diagram_to_iac/agents/shell_langgraph/__init__.py
diagram_to_iac/agents/shell_langgraph/agent.py
diagram_to_iac/agents/shell_langgraph/detector.py
diagram_to_iac/agents/supervisor_langgraph/__init__.py
diagram_to_iac/agents/supervisor_langgraph/agent.py
diagram_to_iac/agents/supervisor_langgraph/config.yaml
diagram_to_iac/agents/supervisor_langgraph/demonstrator.py
diagram_to_iac/agents/supervisor_langgraph/github_listener.py
diagram_to_iac/agents/supervisor_langgraph/guards.py
diagram_to_iac/agents/supervisor_langgraph/pat_loop.py
diagram_to_iac/agents/supervisor_langgraph/router.py
diagram_to_iac/agents/terraform_langgraph/__init__.py
diagram_to_iac/agents/terraform_langgraph/agent.py
diagram_to_iac/agents/terraform_langgraph/config.yaml
diagram_to_iac/agents/terraform_langgraph/parser.py
diagram_to_iac/core/__init__.py
diagram_to_iac/core/agent_base.py
diagram_to_iac-1.19.0.dist-info/METADATA
diagram_to_iac-1.19.0.dist-info/WHEEL
diagram_to_iac-1.19.0.dist-info/entry_points.txt
diagram_to_iac-1.19.0.dist-info/top_level.txt
diagram_to_iac-1.19.0.dist-info/RECORD
