Metadata-Version: 2.4
Name: diagram-to-iac
Version: 1.19.0
Summary: Convert architecture diagrams into IaC modules
Author-email: vindpro <admin@vindpro.com>
Requires-Dist: anthropic==0.57.1
Requires-Dist: google_api_python_client==2.175.0
Requires-Dist: langchain_anthropic==0.3.17
Requires-Dist: langchain-core<1.0.0,>=0.3.62
Requires-Dist: langchain_google_genai==2.1.6
Requires-Dist: langchain_openai==0.3.27
Requires-Dist: langgraph==0.5.1
Requires-Dist: openai==1.93.2
Requires-Dist: protobuf>=5.27.0
Requires-Dist: pydantic==2.11.7
Requires-Dist: PyYAML==6.0.2
Requires-Dist: Requests==2.32.4
Requires-Dist: typing_extensions==4.14.1
Requires-Dist: GitPython<4.0,>=3.1
Provides-Extra: test
Requires-Dist: pytest>=7.0; extra == "test"
Requires-Dist: pytest-cov>=4.0; extra == "test"
Requires-Dist: pytest-mock>=3.10; extra == "test"
Requires-Dist: pytest-asyncio>=0.21; extra == "test"
Requires-Dist: pexpect>=4.8; extra == "test"
